EMOIdentifier/__init__.py
EMOIdentifier/run.py
EMOIdentifier/brace_remover/__init__.py
EMOIdentifier/brace_remover/removeBraces.py
EMOIdentifier/ncec/__init__.py
EMOIdentifier/ncec/config.py
EMOIdentifier/ncec/dotGenerator.py
EMOIdentifier/ncec/esc.py
EMOIdentifier/ncec/generateParameters.py
EMOIdentifier/ncec/graph.py
EMOIdentifier/ncec/graph_3.py
EMOIdentifier/ncec/main.py
EMOIdentifier/ncec/metric.py
EMOIdentifier/ncec/metric_3.py
EMOIdentifier/ncec/metric_FirstSPE_submission.py
EMOIdentifier/ncec/ncec.py
EMOIdentifier/ncec/ncec_3.py
EMOIdentifier/ncec/output.py
EMOIdentifier/ncec/populateVHash.py
EMOIdentifier/ncec/precomputation.py
EMOIdentifier/ncec/removeBraces.py
EMOIdentifier/ncec/sddc.py
EMOIdentifier/ncec/sdgExtractor.py
EMOIdentifier/ncec/segmentation.py
EMOIdentifier-1.0.2.dist-info/DESCRIPTION.rst
EMOIdentifier-1.0.2.dist-info/METADATA
EMOIdentifier-1.0.2.dist-info/RECORD
EMOIdentifier-1.0.2.dist-info/WHEEL
EMOIdentifier-1.0.2.dist-info/metadata.json
EMOIdentifier-1.0.2.dist-info/top_level.txt
segmentIdentifier/__init__.py
segmentIdentifier/run.py
segmentIdentifier/brace_remover/__init__.py
segmentIdentifier/brace_remover/removeBraces.py
segmentIdentifier/ncec/__init__.py
segmentIdentifier/ncec/config.py
segmentIdentifier/ncec/dotGenerator.py
segmentIdentifier/ncec/esc.py
segmentIdentifier/ncec/generateParameters.py
segmentIdentifier/ncec/graph.py
segmentIdentifier/ncec/main.py
segmentIdentifier/ncec/metric.py
segmentIdentifier/ncec/ncec.py
segmentIdentifier/ncec/output.py
segmentIdentifier/ncec/populateVHash.py
segmentIdentifier/ncec/precomputation.py
segmentIdentifier/ncec/sddc.py
segmentIdentifier/ncec/sdgExtractor.py
segmentIdentifier/ncec/segmentation.py
segmentRefactor/__init__.py
segmentRefactor/run.py
segmentRefactor/brace_remover/__init__.py
segmentRefactor/brace_remover/removeBraces.py
segmentRefactor/ncec/__init__.py
segmentRefactor/ncec/config.py
segmentRefactor/ncec/dotGenerator.py
segmentRefactor/ncec/esc.py
segmentRefactor/ncec/generateParameters.py
segmentRefactor/ncec/graph.py
segmentRefactor/ncec/graph_3.py
segmentRefactor/ncec/main.py
segmentRefactor/ncec/metric.py
segmentRefactor/ncec/metric_3.py
